{
  "all": {
    "type": "line",
    "data": {
      "labels": [
        "Day 1-1",
        "Day 1-2",
        "Day 2-1",
        "Day 2-2",
        "Day 3-1",
        "Day 3-2",
        "Day 4-1",
        "Day 4-2",
        "Day 5-1",
        "Day 5-2",
        "Day 6-1",
        "Day 6-2",
        "Day 7-1",
        "Day 7-2",
        "Day 8-1",
        "Day 8-2",
        "Day 9-1",
        "Day 9-2",
        "Day 10-1",
        "Day 10-2",
        "Day 11-1",
        "Day 11-2",
        "Day 12-1",
        "Day 12-2",
        "Day 13-1",
        "Day 13-2",
        "Day 14-1",
        "Day 14-2",
        "Day 15-1",
        "Day 15-2",
        "Day 16-1",
        "Day 16-2",
        "Day 17-1",
        "Day 17-2",
        "Day 18-1",
        "Day 18-2",
        "Day 19-1",
        "Day 19-2",
        "Day 20-1",
        "Day 20-2",
        "Day 21-1",
        "Day 21-2",
        "Day 22-1",
        "Day 22-2",
        "Day 23-1",
        "Day 23-2",
        "Day 24-1",
        "Day 24-2",
        "Day 25-1",
        "Day 25-2"
      ],
      "datasets": [
        {
          "label": "Sergey Ilyevsky",
          "data": [
            64,
            126,
            172,
            211,
            254,
            303,
            352,
            429,
            476,
            519,
            591,
            662,
            712,
            755,
            823,
            888,
            963,
            988,
            1007,
            1071,
            1131,
            1174,
            1219,
            1261,
            1290,
            1322,
            1354,
            1376,
            1416,
            1472,
            1503,
            1545,
            1572,
            1586,
            1602,
            1616,
            1633,
            1650,
            1683,
            1712,
            1728,
            1748,
            1773,
            1795,
            1811,
            1818,
            1819,
            1825,
            1852,
            1892
          ],
          "fill": false
        },
        {
          "label": "Shahar Talmi",
          "data": [
            59,
            120,
            164,
            200,
            247,
            297,
            345,
            416,
            466,
            510,
            579,
            648,
            703,
            748,
            813,
            877,
            946,
            966,
            984,
            1047,
            1103,
            1142,
            1188,
            1227,
            1255,
            1289,
            1318,
            1338,
            1375,
            1430,
            1457,
            1496,
            1524,
            1537,
            1555,
            1574,
            1594,
            1610,
            1642,
            1670,
            1684,
            1706,
            1729,
            1749,
            1763,
            1769,
            1769,
            1785,
            1818,
            1864
          ],
          "fill": false
        },
        {
          "label": "ykrukovsky",
          "data": [
            62,
            121,
            168,
            209,
            254,
            305,
            355,
            433,
            481,
            517,
            591,
            665,
            719,
            761,
            823,
            883,
            959,
            985,
            1005,
            1070,
            1125,
            1156,
            1206,
            1230,
            1253,
            1278,
            1311,
            1334,
            1375,
            1433,
            1463,
            1500,
            1529,
            1539,
            1556,
            1561,
            1582,
            1600,
            1635,
            1662,
            1679,
            1691,
            1710,
            1727,
            1745,
            1742,
            1744,
            1754,
            1776,
            1811
          ],
          "fill": false
        },
        {
          "label": "rasmus93",
          "data": [
            63,
            126,
            171,
            211,
            257,
            309,
            355,
            431,
            477,
            522,
            595,
            668,
            705,
            736,
            805,
            867,
            941,
            965,
            982,
            1041,
            1099,
            1141,
            1190,
            1234,
            1264,
            1295,
            1326,
            1347,
            1385,
            1442,
            1465,
            1501,
            1527,
            1539,
            1553,
            1570,
            1588,
            1603,
            1634,
            1660,
            1675,
            1665,
            1685,
            1703,
            1718,
            1723,
            1722,
            1721,
            1751,
            1794
          ],
          "fill": false
        },
        {
          "label": "Stepan Samko",
          "data": [
            61,
            113,
            155,
            192,
            234,
            282,
            329,
            404,
            449,
            489,
            557,
            625,
            664,
            698,
            762,
            825,
            898,
            920,
            935,
            997,
            1054,
            1092,
            1139,
            1180,
            1199,
            1225,
            1250,
            1269,
            1302,
            1355,
            1377,
            1410,
            1433,
            1442,
            1461,
            1481,
            1496,
            1510,
            1538,
            1550,
            1563,
            1577,
            1601,
            1622,
            1634,
            1637,
            1630,
            1638,
            1670,
            1715
          ],
          "fill": false
        },
        {
          "label": "Ivan Vyshnevskyi",
          "data": [
            42,
            84,
            127,
            165,
            192,
            226,
            262,
            335,
            384,
            426,
            497,
            567,
            613,
            653,
            720,
            781,
            852,
            875,
            881,
            942,
            1001,
            1045,
            1088,
            1128,
            1155,
            1188,
            1152,
            1119,
            1158,
            1212,
            1241,
            1282,
            1306,
            1317,
            1330,
            1319,
            1338,
            1321,
            1355,
            1337,
            1347,
            1330,
            1320,
            1307,
            1320,
            1296,
            1300,
            1313,
            1344,
            1388
          ],
          "fill": false
        },
        {
          "label": "Daniel Kochavi",
          "data": [
            49,
            106,
            142,
            175,
            196,
            226,
            265,
            326,
            364,
            403,
            458,
            515,
            560,
            598,
            656,
            713,
            775,
            784,
            798,
            844,
            894,
            929,
            963,
            997,
            1015,
            1037,
            1060,
            1075,
            1110,
            1158,
            1169,
            1193,
            1214,
            1217,
            1223,
            1230,
            1239,
            1248,
            1266,
            1287,
            1291,
            1307,
            1329,
            1345,
            1332,
            1310,
            1306,
            1317,
            1346,
            1388
          ],
          "fill": false
        },
        {
          "label": "Tomas Peluritis",
          "data": [
            57,
            112,
            150,
            180,
            218,
            219,
            209,
            247,
            281,
            244,
            309,
            375,
            426,
            461,
            520,
            569,
            641,
            662,
            669,
            688,
            749,
            783,
            827,
            862,
            884,
            911,
            941,
            946,
            982,
            1034,
            1058,
            1093,
            1104,
            1103,
            1112,
            1127,
            1139,
            1151,
            1171,
            1193,
            1205,
            1224,
            1245,
            1264,
            1281,
            1285,
            1277,
            1292,
            1320,
            1361
          ],
          "fill": false
        },
        {
          "label": "Guy Porges",
          "data": [
            45,
            85,
            118,
            146,
            183,
            221,
            255,
            324,
            367,
            405,
            467,
            530,
            574,
            615,
            671,
            717,
            785,
            804,
            800,
            817,
            864,
            893,
            900,
            911,
            931,
            960,
            986,
            999,
            1031,
            1081,
            1090,
            1112,
            1134,
            1116,
            1117,
            1113,
            1129,
            1139,
            1166,
            1174,
            1183,
            1193,
            1210,
            1224,
            1226,
            1215,
            1213,
            1207,
            1232,
            1270
          ],
          "fill": false
        },
        {
          "label": "Domantas Slėnys",
          "data": [
            33,
            77,
            78,
            76,
            93,
            117,
            152,
            206,
            233,
            253,
            313,
            375,
            413,
            442,
            493,
            552,
            606,
            610,
            613,
            670,
            719,
            756,
            773,
            801,
            825,
            853,
            881,
            897,
            928,
            979,
            1004,
            1038,
            1055,
            1059,
            1070,
            1086,
            1097,
            1110,
            1122,
            1140,
            1142,
            1146,
            1164,
            1179,
            1184,
            1178,
            1150,
            1151,
            1171,
            1204
          ],
          "fill": false
        },
        {
          "label": "GregoryNative",
          "data": [
            48,
            98,
            138,
            172,
            204,
            245,
            278,
            335,
            367,
            391,
            440,
            491,
            527,
            551,
            605,
            661,
            716,
            721,
            713,
            767,
            808,
            838,
            878,
            914,
            931,
            919,
            916,
            902,
            928,
            974,
            995,
            1027,
            1047,
            1055,
            1025,
            1001,
            1007,
            993,
            1022,
            1021,
            1022,
            1013,
            1012,
            1005,
            1004,
            1003,
            992,
            990,
            1007,
            1037
          ],
          "fill": false
        },
        {
          "label": "Matan Keidar",
          "data": [
            60,
            66,
            105,
            137,
            160,
            192,
            230,
            224,
            212,
            230,
            282,
            336,
            357,
            380,
            363,
            370,
            427,
            434,
            422,
            480,
            511,
            531,
            579,
            622,
            635,
            659,
            671,
            683,
            710,
            751,
            770,
            800,
            819,
            826,
            829,
            840,
            844,
            852,
            873,
            889,
            879,
            892,
            906,
            909,
            906,
            901,
            878,
            880,
            903,
            939
          ],
          "fill": false
        },
        {
          "label": "Anton Kolhun",
          "data": [
            38,
            87,
            113,
            139,
            136,
            143,
            175,
            243,
            282,
            256,
            287,
            318,
            366,
            402,
            465,
            520,
            584,
            599,
            597,
            580,
            604,
            595,
            633,
            663,
            679,
            700,
            727,
            744,
            778,
            827,
            845,
            874,
            873,
            861,
            871,
            870,
            878,
            874,
            893,
            908,
            919,
            930,
            926,
            921,
            915,
            892,
            868,
            858,
            859,
            876
          ],
          "fill": false
        },
        {
          "label": "Snir Sharristh",
          "data": [
            -11,
            -6,
            -41,
            -77,
            -73,
            -56,
            -48,
            1,
            0,
            4,
            48,
            93,
            136,
            168,
            218,
            266,
            317,
            318,
            328,
            380,
            418,
            443,
            484,
            521,
            530,
            549,
            567,
            577,
            560,
            568,
            571,
            588,
            601,
            602,
            614,
            632,
            645,
            656,
            679,
            702,
            710,
            728,
            731,
            732,
            728,
            724,
            718,
            730,
            751,
            785
          ],
          "fill": false
        },
        {
          "label": "Lior Hai",
          "data": [
            32,
            64,
            94,
            109,
            135,
            161,
            102,
            88,
            107,
            141,
            173,
            205,
            207,
            174,
            205,
            216,
            268,
            270,
            263,
            308,
            341,
            357,
            390,
            403,
            395,
            397,
            407,
            387,
            415,
            460,
            461,
            476,
            490,
            486,
            468,
            459,
            464,
            456,
            461,
            468,
            473,
            476,
            491,
            503,
            513,
            505,
            500,
            509,
            527,
            558
          ],
          "fill": false
        },
        {
          "label": "Domas Maksimas",
          "data": [
            47,
            86,
            84,
            76,
            89,
            111,
            121,
            148,
            172,
            162,
            191,
            221,
            246,
            249,
            288,
            333,
            328,
            275,
            264,
            307,
            351,
            366,
            395,
            400,
            411,
            412,
            431,
            439,
            463,
            502,
            472,
            454,
            443,
            420,
            422,
            428,
            430,
            432,
            454,
            479,
            478,
            495,
            511,
            524,
            527,
            520,
            501,
            504,
            507,
            526
          ],
          "fill": false
        },
        {
          "label": "Amit Dahan",
          "data": [
            -7,
            0,
            5,
            7,
            17,
            35,
            38,
            71,
            87,
            120,
            150,
            179,
            193,
            188,
            221,
            208,
            241,
            225,
            220,
            271,
            299,
            313,
            318,
            332,
            327,
            336,
            347,
            356,
            371,
            384,
            397,
            423,
            435,
            435,
            434,
            444,
            445,
            452,
            469,
            486,
            481,
            496,
            506,
            516,
            507,
            498,
            483,
            479,
            495,
            524
          ],
          "fill": false
        },
        {
          "label": "Yehor Chornyi",
          "data": [
            4,
            -10,
            -14,
            -20,
            4,
            37,
            57,
            108,
            136,
            148,
            199,
            247,
            287,
            315,
            359,
            360,
            421,
            434,
            445,
            486,
            523,
            541,
            562,
            583,
            608,
            615,
            635,
            601,
            631,
            675,
            695,
            726,
            695,
            651,
            646,
            608,
            622,
            598,
            578,
            556,
            526,
            505,
            483,
            459,
            449,
            416,
            379,
            356,
            352,
            358
          ],
          "fill": false
        },
        {
          "label": "Rėjus Paukštė",
          "data": [
            31,
            62,
            77,
            87,
            86,
            89,
            100,
            148,
            185,
            171,
            221,
            270,
            304,
            277,
            299,
            333,
            371,
            361,
            338,
            372,
            360,
            331,
            329,
            322,
            332,
            346,
            348,
            347,
            363,
            396,
            390,
            396,
            404,
            401,
            380,
            375,
            355,
            346,
            348,
            342,
            321,
            318,
            316,
            313,
            314,
            315,
            298,
            303,
            303,
            319
          ],
          "fill": false
        },
        {
          "label": "Taras Petushkov",
          "data": [
            -10,
            0,
            0,
            0,
            -9,
            0,
            -24,
            0,
            1,
            17,
            24,
            30,
            21,
            15,
            19,
            44,
            62,
            34,
            12,
            56,
            65,
            60,
            84,
            116,
            115,
            128,
            90,
            66,
            64,
            87,
            97,
            122,
            140,
            145,
            139,
            142,
            140,
            144,
            158,
            178,
            169,
            178,
            191,
            202,
            206,
            204,
            183,
            178,
            191,
            217
          ],
          "fill": false
        },
        {
          "label": "Nachshon Schwartz",
          "data": [
            -78,
            -145,
            -202,
            -262,
            -228,
            -185,
            -256,
            -286,
            -265,
            -303,
            -267,
            -231,
            -200,
            -185,
            -151,
            -121,
            -134,
            -195,
            -216,
            -211,
            -176,
            -155,
            -116,
            -83,
            -80,
            -65,
            -48,
            -64,
            -44,
            -4,
            -23,
            -31,
            -6,
            0,
            5,
            17,
            24,
            13,
            39,
            44,
            47,
            52,
            59,
            48,
            30,
            10,
            0,
            0,
            26,
            65
          ],
          "fill": false
        },
        {
          "label": "Almog Adziashvili",
          "data": [
            36,
            83,
            59,
            32,
            24,
            30,
            16,
            53,
            16,
            0,
            0,
            0,
            0,
            0,
            -39,
            -74,
            -80,
            -134,
            -133,
            -80,
            -64,
            -63,
            -38,
            -7,
            -26,
            -32,
            -23,
            -20,
            -33,
            -23,
            -18,
            0,
            16,
            11,
            0,
            0,
            -12,
            -14,
            -8,
            -4,
            -10,
            -8,
            -4,
            0,
            0,
            0,
            3,
            17,
            32,
            60
          ],
          "fill": false
        },
        {
          "label": "Oleksandr Bondarchuk",
          "data": [
            56,
            116,
            150,
            156,
            152,
            162,
            141,
            170,
            205,
            175,
            221,
            267,
            319,
            358,
            419,
            448,
            463,
            431,
            418,
            458,
            469,
            467,
            463,
            438,
            409,
            391,
            347,
            310,
            313,
            338,
            366,
            406,
            401,
            380,
            358,
            348,
            322,
            286,
            283,
            268,
            232,
            205,
            187,
            168,
            138,
            104,
            62,
            32,
            39,
            41
          ],
          "fill": false
        },
        {
          "label": "Lev Vidrak",
          "data": [
            -18,
            -26,
            -92,
            -162,
            -219,
            -261,
            -247,
            -247,
            -239,
            -214,
            -169,
            -125,
            -98,
            -123,
            -86,
            -49,
            0,
            0,
            0,
            0,
            45,
            73,
            50,
            39,
            53,
            73,
            97,
            104,
            133,
            176,
            188,
            211,
            177,
            130,
            113,
            76,
            86,
            76,
            106,
            116,
            123,
            118,
            111,
            102,
            82,
            55,
            46,
            14,
            0,
            0
          ],
          "fill": false
        },
        {
          "label": "Dziugas Untulis",
          "data": [
            -4,
            -3,
            19,
            38,
            0,
            -25,
            0,
            60,
            58,
            77,
            124,
            171,
            200,
            222,
            277,
            330,
            353,
            331,
            280,
            301,
            295,
            271,
            274,
            252,
            210,
            181,
            126,
            75,
            43,
            33,
            9,
            -4,
            0,
            -9,
            -2,
            0,
            0,
            0,
            0,
            0,
            0,
            0,
            0,
            -1,
            -8,
            -21,
            -47,
            -58,
            -60,
            -46
          ],
          "fill": false
        },
        {
          "label": "Dima Bildin",
          "data": [
            -31,
            -48,
            -71,
            -97,
            -136,
            -165,
            -178,
            -143,
            -137,
            -128,
            -104,
            -82,
            -71,
            -58,
            -50,
            -27,
            0,
            -19,
            -47,
            -19,
            0,
            0,
            0,
            0,
            0,
            0,
            0,
            0,
            0,
            0,
            0,
            14,
            -7,
            -40,
            -67,
            -88,
            -92,
            -110,
            -94,
            -75,
            -100,
            -104,
            -103,
            -103,
            -105,
            -124,
            -142,
            -145,
            -131,
            -104
          ],
          "fill": false
        },
        {
          "label": "Jonathan Fraimorice",
          "data": [
            28,
            17,
            -28,
            -76,
            -83,
            -72,
            -105,
            -87,
            -91,
            -62,
            -70,
            -78,
            -72,
            -62,
            -80,
            -78,
            -47,
            -64,
            -70,
            -10,
            -11,
            -27,
            -25,
            -18,
            -36,
            -40,
            -75,
            -92,
            -100,
            -84,
            -67,
            -68,
            -59,
            -61,
            -75,
            -77,
            -101,
            -114,
            -116,
            -115,
            -132,
            -134,
            -128,
            -121,
            -140,
            -158,
            -189,
            -201,
            -182,
            -150
          ],
          "fill": false
        },
        {
          "label": "Vytenis Urbonavičius",
          "data": [
            7,
            30,
            -7,
            -47,
            -88,
            -111,
            -137,
            -116,
            -114,
            -88,
            -78,
            -68,
            -65,
            -60,
            -46,
            -11,
            -11,
            -58,
            -95,
            -65,
            -53,
            -65,
            -80,
            -88,
            -92,
            -82,
            -110,
            -121,
            -114,
            -87,
            -95,
            -90,
            -96,
            -111,
            -143,
            -166,
            -184,
            -189,
            -185,
            -179,
            -187,
            -181,
            -172,
            -163,
            -177,
            -192,
            -219,
            -215,
            -216,
            -201
          ],
          "fill": false
        },
        {
          "label": "Tomer Groisman",
          "data": [
            -92,
            -168,
            -241,
            -317,
            -329,
            -324,
            -332,
            -301,
            -322,
            -324,
            -266,
            -208,
            -204,
            -198,
            -180,
            -202,
            -183,
            -212,
            -199,
            -185,
            -142,
            -135,
            -107,
            -89,
            -128,
            -159,
            -198,
            -225,
            -216,
            -188,
            -162,
            -124,
            -147,
            -179,
            -198,
            -206,
            -231,
            -258,
            -263,
            -271,
            -295,
            -288,
            -277,
            -269,
            -258,
            -256,
            -259,
            -266,
            -261,
            -240
          ],
          "fill": false
        },
        {
          "label": "Yevhen Kramorenko",
          "data": [
            8,
            25,
            -1,
            -30,
            -81,
            -116,
            -135,
            -105,
            -92,
            -62,
            -40,
            -17,
            -31,
            -49,
            -39,
            -43,
            -32,
            -72,
            -105,
            -72,
            -75,
            -93,
            -81,
            -85,
            -88,
            -77,
            -120,
            -151,
            -163,
            -151,
            -162,
            -158,
            -155,
            -168,
            -180,
            -197,
            -220,
            -241,
            -231,
            -228,
            -246,
            -252,
            -244,
            -238,
            -243,
            -264,
            -286,
            -300,
            -288,
            -263
          ],
          "fill": false
        },
        {
          "label": "dragonofdeath",
          "data": [
            -62,
            -107,
            -123,
            -142,
            -139,
            -124,
            -207,
            -254,
            -305,
            -383,
            -368,
            -353,
            -330,
            -310,
            -280,
            -249,
            -207,
            -213,
            -251,
            -225,
            -241,
            -271,
            -298,
            -313,
            -353,
            -381,
            -377,
            -375,
            -397,
            -396,
            -388,
            -367,
            -357,
            -365,
            -388,
            -395,
            -392,
            -389,
            -365,
            -341,
            -345,
            -344,
            -332,
            -334,
            -325,
            -337,
            -349,
            -342,
            -347,
            -334
          ],
          "fill": false
        },
        {
          "label": "Justas Valskis",
          "data": [
            30,
            71,
            87,
            98,
            93,
            65,
            74,
            124,
            136,
            139,
            173,
            207,
            224,
            225,
            192,
            164,
            142,
            74,
            12,
            2,
            -18,
            -54,
            -83,
            -120,
            -119,
            -114,
            -109,
            -108,
            -90,
            -55,
            -92,
            -118,
            -133,
            -160,
            -164,
            -180,
            -193,
            -223,
            -251,
            -280,
            -300,
            -314,
            -331,
            -351,
            -372,
            -407,
            -450,
            -481,
            -493,
            -492
          ],
          "fill": false
        },
        {
          "label": "Dalius Krivickas",
          "data": [
            0,
            -12,
            23,
            54,
            61,
            41,
            1,
            -2,
            -25,
            -54,
            -36,
            -18,
            -21,
            -29,
            0,
            0,
            -10,
            -67,
            -113,
            -118,
            -115,
            -125,
            -128,
            -133,
            -148,
            -174,
            -179,
            -197,
            -204,
            -189,
            -199,
            -196,
            -213,
            -264,
            -280,
            -300,
            -311,
            -331,
            -338,
            -347,
            -373,
            -380,
            -386,
            -394,
            -409,
            -447,
            -481,
            -505,
            -513,
            -504
          ],
          "fill": false
        },
        {
          "label": "Artem Ohanjanyan",
          "data": [
            -76,
            -139,
            -190,
            -245,
            -265,
            -270,
            -300,
            -298,
            -308,
            -306,
            -300,
            -292,
            -283,
            -274,
            -290,
            -282,
            -305,
            -376,
            -400,
            -358,
            -344,
            -342,
            -366,
            -378,
            -410,
            -430,
            -416,
            -405,
            -434,
            -440,
            -449,
            -448,
            -447,
            -457,
            -460,
            -456,
            -459,
            -454,
            -439,
            -446,
            -458,
            -469,
            -483,
            -501,
            -532,
            -564,
            -608,
            -635,
            -645,
            -638
          ],
          "fill": false
        },
        {
          "label": "PenzK",
          "data": [
            -43,
            -72,
            -87,
            -107,
            -134,
            -156,
            -197,
            -190,
            -221,
            -222,
            -219,
            -217,
            -243,
            -273,
            -295,
            -302,
            -290,
            -325,
            -355,
            -324,
            -329,
            -352,
            -358,
            -352,
            -379,
            -395,
            -436,
            -465,
            -483,
            -477,
            -494,
            -500,
            -498,
            -518,
            -549,
            -563,
            -584,
            -591,
            -600,
            -612,
            -644,
            -659,
            -670,
            -684,
            -710,
            -739,
            -771,
            -786,
            -777,
            -754
          ],
          "fill": false
        },
        {
          "label": "Donatas Petrauskas",
          "data": [
            -72,
            -133,
            -143,
            -155,
            -187,
            -203,
            -191,
            -139,
            -122,
            -187,
            -238,
            -289,
            -345,
            -408,
            -449,
            -488,
            -503,
            -566,
            -611,
            -591,
            -537,
            -496,
            -490,
            -493,
            -528,
            -558,
            -606,
            -655,
            -681,
            -685,
            -679,
            -667,
            -680,
            -706,
            -702,
            -694,
            -701,
            -713,
            -688,
            -691,
            -713,
            -714,
            -709,
            -704,
            -698,
            -723,
            -756,
            -777,
            -784,
            -774
          ],
          "fill": false
        },
        {
          "label": "Yuval Shavit",
          "data": [
            -112,
            -205,
            -296,
            -409,
            -498,
            -576,
            -596,
            -649,
            -712,
            -760,
            -767,
            -773,
            -813,
            -855,
            -869,
            -859,
            -818,
            -825,
            -868,
            -831,
            -816,
            -813,
            -790,
            -761,
            -763,
            -751,
            -765,
            -773,
            -796,
            -797,
            -825,
            -841,
            -849,
            -866,
            -868,
            -859,
            -865,
            -859,
            -851,
            -837,
            -844,
            -823,
            -826,
            -830,
            -841,
            -851,
            -880,
            -888,
            -878,
            -854
          ],
          "fill": false
        },
        {
          "label": "Gil Galditzky",
          "data": [
            -42,
            -79,
            -104,
            -132,
            -192,
            -237,
            -304,
            -326,
            -364,
            -382,
            -402,
            -422,
            -445,
            -468,
            -448,
            -415,
            -394,
            -427,
            -488,
            -477,
            -485,
            -505,
            -504,
            -487,
            -512,
            -526,
            -547,
            -577,
            -571,
            -560,
            -583,
            -594,
            -608,
            -632,
            -670,
            -695,
            -733,
            -761,
            -767,
            -771,
            -804,
            -817,
            -825,
            -835,
            -851,
            -867,
            -902,
            -919,
            -917,
            -899
          ],
          "fill": false
        },
        {
          "label": "Ted Kostylev",
          "data": [
            -24,
            -33,
            -52,
            -75,
            -136,
            -197,
            -220,
            -206,
            -202,
            -206,
            -190,
            -173,
            -185,
            -202,
            -197,
            -173,
            -153,
            -178,
            -235,
            -243,
            -242,
            -255,
            -285,
            -304,
            -342,
            -377,
            -430,
            -480,
            -511,
            -529,
            -564,
            -588,
            -616,
            -657,
            -704,
            -740,
            -783,
            -820,
            -838,
            -855,
            -894,
            -910,
            -922,
            -937,
            -959,
            -985,
            -1015,
            -1024,
            -1000,
            -963
          ],
          "fill": false
        },
        {
          "label": "Maurits Out",
          "data": [
            -58,
            -104,
            -135,
            -168,
            -194,
            -225,
            -268,
            -269,
            -299,
            -341,
            -351,
            -368,
            -385,
            -414,
            -403,
            -385,
            -380,
            -423,
            -449,
            -422,
            -426,
            -452,
            -461,
            -489,
            -530,
            -563,
            -615,
            -662,
            -681,
            -677,
            -693,
            -698,
            -701,
            -717,
            -741,
            -769,
            -806,
            -840,
            -857,
            -873,
            -911,
            -937,
            -958,
            -981,
            -1013,
            -1050,
            -1091,
            -1113,
            -1102,
            -1098
          ],
          "fill": false
        },
        {
          "label": "Siril-O",
          "data": [
            -113,
            -209,
            -303,
            -401,
            -486,
            -562,
            -642,
            -687,
            -728,
            -751,
            -750,
            -749,
            -771,
            -793,
            -786,
            -767,
            -742,
            -766,
            -797,
            -773,
            -760,
            -766,
            -748,
            -732,
            -745,
            -746,
            -775,
            -790,
            -779,
            -758,
            -770,
            -768,
            -772,
            -812,
            -837,
            -859,
            -873,
            -879,
            -878,
            -876,
            -892,
            -920,
            -944,
            -970,
            -1006,
            -1047,
            -1095,
            -1124,
            -1137,
            -1134
          ],
          "fill": false
        },
        {
          "label": "Shachar Almagor",
          "data": [
            -98,
            -177,
            -254,
            -346,
            -419,
            -481,
            -517,
            -506,
            -523,
            -584,
            -629,
            -674,
            -662,
            -651,
            -689,
            -721,
            -711,
            -748,
            -822,
            -837,
            -861,
            -899,
            -927,
            -943,
            -976,
            -998,
            -997,
            -1001,
            -1036,
            -1050,
            -1082,
            -1103,
            -1119,
            -1144,
            -1180,
            -1199,
            -1214,
            -1233,
            -1222,
            -1213,
            -1228,
            -1220,
            -1225,
            -1231,
            -1248,
            -1265,
            -1285,
            -1298,
            -1294,
            -1274
          ],
          "fill": false
        },
        {
          "label": "Dalius Krivickas",
          "data": [
            0,
            -12,
            23,
            54,
            61,
            41,
            1,
            -2,
            -25,
            -54,
            -36,
            -18,
            -21,
            -29,
            0,
            0,
            -10,
            -67,
            -113,
            -118,
            -115,
            -125,
            -128,
            -133,
            -148,
            -174,
            -179,
            -197,
            -204,
            -189,
            -199,
            -196,
            -213,
            -264,
            -280,
            -300,
            -311,
            -331,
            -338,
            -347,
            -373,
            -380,
            -386,
            -394,
            -409,
            -447,
            -481,
            -505,
            -513,
            -504
          ],
          "fill": false
        },
        {
          "label": "Leonid Kolomiitsev",
          "data": [
            -13,
            -13,
            -55,
            -97,
            -155,
            -196,
            -254,
            -267,
            -314,
            -341,
            -381,
            -421,
            -480,
            -545,
            -591,
            -635,
            -664,
            -744,
            -817,
            -828,
            -859,
            -910,
            -943,
            -966,
            -1012,
            -1049,
            -1103,
            -1155,
            -1194,
            -1215,
            -1254,
            -1282,
            -1301,
            -1332,
            -1378,
            -1413,
            -1454,
            -1487,
            -1501,
            -1521,
            -1555,
            -1573,
            -1582,
            -1594,
            -1617,
            -1645,
            -1683,
            -1701,
            -1707,
            -1696
          ],
          "fill": false
        },
        {
          "label": "Michael Wachsman",
          "data": [
            -101,
            -185,
            -274,
            -368,
            -451,
            -522,
            -600,
            -641,
            -709,
            -783,
            -832,
            -881,
            -910,
            -965,
            -972,
            -1008,
            -1020,
            -1097,
            -1147,
            -1166,
            -1195,
            -1239,
            -1256,
            -1280,
            -1300,
            -1307,
            -1340,
            -1368,
            -1379,
            -1387,
            -1423,
            -1448,
            -1468,
            -1498,
            -1535,
            -1567,
            -1611,
            -1643,
            -1659,
            -1678,
            -1715,
            -1734,
            -1749,
            -1765,
            -1793,
            -1823,
            -1862,
            -1881,
            -1875,
            -1853
          ],
          "fill": false
        },
        {
          "label": "kateryname",
          "data": [
            -59,
            -108,
            -175,
            -247,
            -293,
            -348,
            -390,
            -429,
            -523,
            -605,
            -662,
            -719,
            -784,
            -855,
            -907,
            -958,
            -1003,
            -1097,
            -1193,
            -1229,
            -1273,
            -1332,
            -1370,
            -1399,
            -1454,
            -1498,
            -1560,
            -1617,
            -1659,
            -1682,
            -1724,
            -1755,
            -1790,
            -1838,
            -1889,
            -1928,
            -1975,
            -2013,
            -2032,
            -2053,
            -2094,
            -2114,
            -2130,
            -2147,
            -2176,
            -2207,
            -2247,
            -2267,
            -2270,
            -2258
          ],
          "fill": false
        },
        {
          "label": "Oran Shuster",
          "data": [
            -47,
            -102,
            -230,
            -361,
            -479,
            -586,
            -697,
            -773,
            -868,
            -951,
            -1015,
            -1079,
            -1154,
            -1236,
            -1298,
            -1359,
            -1407,
            -1504,
            -1602,
            -1641,
            -1689,
            -1752,
            -1794,
            -1830,
            -1890,
            -1940,
            -2008,
            -2070,
            -2118,
            -2146,
            -2195,
            -2233,
            -2271,
            -2324,
            -2376,
            -2418,
            -2467,
            -2507,
            -2533,
            -2561,
            -2608,
            -2632,
            -2655,
            -2680,
            -2715,
            -2755,
            -2802,
            -2830,
            -2841,
            -2836
          ],
          "fill": false
        },
        {
          "label": "Dmytro Khomutnyk",
          "data": [
            -5,
            -2,
            -48,
            -97,
            -140,
            -170,
            -187,
            -155,
            -132,
            -117,
            -76,
            -41,
            -15,
            -25,
            20,
            19,
            72,
            75,
            -1,
            -28,
            -54,
            -94,
            -81,
            -79,
            -85,
            -88,
            -89,
            -94,
            -82,
            -52,
            -50,
            -34,
            -71,
            -121,
            -163,
            -194,
            -239,
            -274,
            -298,
            -323,
            -367,
            -389,
            -992,
            -1598,
            -1631,
            -1667,
            -1712,
            -1737
          ],
          "fill": false
        },
        {
          "label": "SofiiaBalushka",
          "data": [
            -127,
            -235,
            -348,
            -464,
            -564,
            -654,
            -750,
            -810,
            -889,
            -961,
            -1017,
            -1073,
            -1136,
            -1206,
            -1253,
            -1305,
            -1339,
            -1422,
            -1508,
            -1548,
            -1566,
            -1598,
            -1608,
            -1604,
            -1614,
            -1606,
            -1628,
            -1666,
            -1653,
            -1621,
            -1643,
            -1655,
            -1695,
            -1750,
            -1783,
            -1826,
            -1834,
            -1835,
            -1848,
            -1872,
            -1914,
            -2520,
            -2539,
            -2560,
            -2584,
            -2626,
            -2651,
            -2684
          ],
          "fill": false
        }
      ]
    }
  },
  "ten": {
    "type": "line",
    "data": {
      "labels": [
        "Day 1-1",
        "Day 1-2",
        "Day 2-1",
        "Day 2-2",
        "Day 3-1",
        "Day 3-2",
        "Day 4-1",
        "Day 4-2",
        "Day 5-1",
        "Day 5-2",
        "Day 6-1",
        "Day 6-2",
        "Day 7-1",
        "Day 7-2",
        "Day 8-1",
        "Day 8-2",
        "Day 9-1",
        "Day 9-2",
        "Day 10-1",
        "Day 10-2",
        "Day 11-1",
        "Day 11-2",
        "Day 12-1",
        "Day 12-2",
        "Day 13-1",
        "Day 13-2",
        "Day 14-1",
        "Day 14-2",
        "Day 15-1",
        "Day 15-2",
        "Day 16-1",
        "Day 16-2",
        "Day 17-1",
        "Day 17-2",
        "Day 18-1",
        "Day 18-2",
        "Day 19-1",
        "Day 19-2",
        "Day 20-1",
        "Day 20-2",
        "Day 21-1",
        "Day 21-2",
        "Day 22-1",
        "Day 22-2",
        "Day 23-1",
        "Day 23-2",
        "Day 24-1",
        "Day 24-2",
        "Day 25-1",
        "Day 25-2"
      ],
      "datasets": [
        {
          "label": "Sergey Ilyevsky",
          "data": [
            5,
            13,
            17,
            19,
            20,
            21,
            23,
            25,
            27,
            30,
            34,
            37,
            48,
            57,
            61,
            63,
            65,
            68,
            72,
            74,
            77,
            82,
            80,
            81,
            91,
            97,
            104,
            107,
            114,
            117,
            126,
            135,
            139,
            144,
            141,
            135,
            137,
            140,
            145,
            162,
            165,
            171,
            172,
            173,
            177,
            181,
            189,
            187,
            182,
            177
          ],
          "fill": false
        },
        {
          "label": "Shahar Talmi",
          "data": [
            0,
            7,
            9,
            8,
            13,
            15,
            16,
            12,
            17,
            21,
            22,
            23,
            39,
            50,
            51,
            52,
            48,
            46,
            49,
            50,
            49,
            50,
            49,
            47,
            56,
            64,
            68,
            69,
            73,
            75,
            80,
            86,
            91,
            95,
            94,
            93,
            98,
            100,
            104,
            120,
            121,
            129,
            128,
            127,
            129,
            132,
            139,
            147,
            148,
            149
          ],
          "fill": false
        },
        {
          "label": "ykrukovsky",
          "data": [
            3,
            8,
            13,
            17,
            20,
            23,
            26,
            29,
            32,
            28,
            34,
            40,
            55,
            63,
            61,
            58,
            61,
            65,
            70,
            73,
            71,
            64,
            67,
            50,
            54,
            53,
            61,
            65,
            73,
            78,
            86,
            90,
            96,
            97,
            95,
            80,
            86,
            90,
            97,
            112,
            116,
            114,
            109,
            105,
            111,
            105,
            114,
            116,
            106,
            96
          ],
          "fill": false
        },
        {
          "label": "rasmus93",
          "data": [
            4,
            13,
            16,
            19,
            23,
            27,
            26,
            27,
            28,
            33,
            38,
            43,
            41,
            38,
            43,
            42,
            43,
            45,
            47,
            44,
            45,
            49,
            51,
            54,
            65,
            70,
            76,
            78,
            83,
            87,
            88,
            91,
            94,
            97,
            92,
            89,
            92,
            93,
            96,
            110,
            112,
            88,
            84,
            81,
            84,
            86,
            92,
            83,
            81,
            79
          ],
          "fill": false
        },
        {
          "label": "Stepan Samko",
          "data": [
            2,
            0,
            0,
            0,
            0,
            0,
            0,
            0,
            0,
            0,
            0,
            0,
            0,
            0,
            0,
            0,
            0,
            0,
            0,
            0,
            0,
            0,
            0,
            0,
            0,
            0,
            0,
            0,
            0,
            0,
            0,
            0,
            0,
            0,
            0,
            0,
            0,
            0,
            0,
            0,
            0,
            0,
            0,
            0,
            0,
            0,
            0,
            0,
            0,
            0
          ],
          "fill": false
        },
        {
          "label": "Ivan Vyshnevskyi",
          "data": [
            -17,
            -29,
            -28,
            -27,
            -42,
            -56,
            -67,
            -69,
            -65,
            -63,
            -60,
            -58,
            -51,
            -45,
            -42,
            -44,
            -46,
            -45,
            -54,
            -55,
            -53,
            -47,
            -51,
            -52,
            -44,
            -37,
            -98,
            -150,
            -144,
            -143,
            -136,
            -128,
            -127,
            -125,
            -131,
            -162,
            -158,
            -189,
            -183,
            -213,
            -216,
            -247,
            -281,
            -315,
            -314,
            -341,
            -330,
            -325,
            -326,
            -327
          ],
          "fill": false
        },
        {
          "label": "Daniel Kochavi",
          "data": [
            -10,
            -7,
            -13,
            -17,
            -38,
            -56,
            -64,
            -78,
            -85,
            -86,
            -99,
            -110,
            -104,
            -100,
            -106,
            -112,
            -123,
            -136,
            -137,
            -153,
            -160,
            -163,
            -176,
            -183,
            -184,
            -188,
            -190,
            -194,
            -192,
            -197,
            -208,
            -217,
            -219,
            -225,
            -238,
            -251,
            -257,
            -262,
            -272,
            -263,
            -272,
            -270,
            -272,
            -277,
            -302,
            -327,
            -324,
            -321,
            -324,
            -327
          ],
          "fill": false
        },
        {
          "label": "Tomas Peluritis",
          "data": [
            -2,
            -1,
            -5,
            -12,
            -16,
            -63,
            -120,
            -157,
            -168,
            -245,
            -248,
            -250,
            -238,
            -237,
            -242,
            -256,
            -257,
            -258,
            -266,
            -309,
            -305,
            -309,
            -312,
            -318,
            -315,
            -314,
            -309,
            -323,
            -320,
            -321,
            -319,
            -317,
            -329,
            -339,
            -349,
            -354,
            -357,
            -359,
            -367,
            -357,
            -358,
            -353,
            -356,
            -358,
            -353,
            -352,
            -353,
            -346,
            -350,
            -354
          ],
          "fill": false
        },
        {
          "label": "Guy Porges",
          "data": [
            -14,
            -28,
            -37,
            -46,
            -51,
            -61,
            -74,
            -80,
            -82,
            -84,
            -90,
            -95,
            -90,
            -83,
            -91,
            -108,
            -113,
            -116,
            -135,
            -180,
            -190,
            -199,
            -239,
            -269,
            -268,
            -265,
            -264,
            -270,
            -271,
            -274,
            -287,
            -298,
            -299,
            -326,
            -344,
            -368,
            -367,
            -371,
            -372,
            -376,
            -380,
            -384,
            -391,
            -398,
            -408,
            -422,
            -417,
            -431,
            -438,
            -445
          ],
          "fill": false
        },
        {
          "label": "Domantas Slėnys",
          "data": [
            -26,
            -36,
            -77,
            -116,
            -141,
            -165,
            -177,
            -198,
            -216,
            -236,
            -244,
            -250,
            -251,
            -256,
            -269,
            -273,
            -292,
            -310,
            -322,
            -327,
            -335,
            -336,
            -366,
            -379,
            -374,
            -372,
            -369,
            -372,
            -374,
            -376,
            -373,
            -372,
            -378,
            -383,
            -391,
            -395,
            -399,
            -400,
            -416,
            -410,
            -421,
            -431,
            -437,
            -443,
            -450,
            -459,
            -480,
            -487,
            -499,
            -511
          ],
          "fill": false
        }
      ]
    }
  },
  "five": {
    "type": "line",
    "data": {
      "labels": [
        "Day 1-1",
        "Day 1-2",
        "Day 2-1",
        "Day 2-2",
        "Day 3-1",
        "Day 3-2",
        "Day 4-1",
        "Day 4-2",
        "Day 5-1",
        "Day 5-2",
        "Day 6-1",
        "Day 6-2",
        "Day 7-1",
        "Day 7-2",
        "Day 8-1",
        "Day 8-2",
        "Day 9-1",
        "Day 9-2",
        "Day 10-1",
        "Day 10-2",
        "Day 11-1",
        "Day 11-2",
        "Day 12-1",
        "Day 12-2",
        "Day 13-1",
        "Day 13-2",
        "Day 14-1",
        "Day 14-2",
        "Day 15-1",
        "Day 15-2",
        "Day 16-1",
        "Day 16-2",
        "Day 17-1",
        "Day 17-2",
        "Day 18-1",
        "Day 18-2",
        "Day 19-1",
        "Day 19-2",
        "Day 20-1",
        "Day 20-2",
        "Day 21-1",
        "Day 21-2",
        "Day 22-1",
        "Day 22-2",
        "Day 23-1",
        "Day 23-2",
        "Day 24-1",
        "Day 24-2",
        "Day 25-1",
        "Day 25-2"
      ],
      "datasets": [
        {
          "label": "Sergey Ilyevsky",
          "data": [
            2,
            5,
            4,
            2,
            0,
            0,
            0,
            0,
            0,
            2,
            0,
            0,
            7,
            7,
            10,
            11,
            17,
            22,
            23,
            24,
            28,
            32,
            29,
            31,
            35,
            33,
            36,
            38,
            41,
            39,
            40,
            45,
            45,
            47,
            47,
            46,
            45,
            47,
            48,
            50,
            49,
            57,
            63,
            68,
            66,
            76,
            75,
            71,
            76,
            81
          ],
          "fill": false
        },
        {
          "label": "Shahar Talmi",
          "data": [
            -3,
            -1,
            -4,
            -9,
            -7,
            -6,
            -7,
            -13,
            -10,
            -7,
            -12,
            -14,
            -2,
            0,
            0,
            0,
            0,
            0,
            0,
            0,
            0,
            0,
            -2,
            -3,
            0,
            0,
            0,
            0,
            0,
            -3,
            -6,
            -4,
            -3,
            -2,
            0,
            4,
            6,
            7,
            7,
            8,
            5,
            15,
            19,
            22,
            18,
            27,
            25,
            31,
            42,
            53
          ],
          "fill": false
        },
        {
          "label": "ykrukovsky",
          "data": [
            0,
            0,
            0,
            0,
            0,
            2,
            3,
            4,
            5,
            0,
            0,
            3,
            14,
            13,
            10,
            6,
            13,
            19,
            21,
            23,
            22,
            14,
            16,
            0,
            -2,
            -11,
            -7,
            -4,
            0,
            0,
            0,
            0,
            2,
            0,
            1,
            -9,
            -6,
            -3,
            0,
            0,
            0,
            0,
            0,
            0,
            0,
            0,
            0,
            0,
            0,
            0
          ],
          "fill": false
        },
        {
          "label": "rasmus93",
          "data": [
            1,
            5,
            3,
            2,
            3,
            6,
            3,
            2,
            1,
            5,
            4,
            6,
            0,
            -12,
            -8,
            -10,
            -5,
            -1,
            -2,
            -6,
            -4,
            -1,
            0,
            4,
            9,
            6,
            8,
            9,
            10,
            9,
            2,
            1,
            0,
            0,
            -2,
            0,
            0,
            0,
            -1,
            -2,
            -4,
            -26,
            -25,
            -24,
            -27,
            -19,
            -22,
            -33,
            -25,
            -17
          ],
          "fill": false
        },
        {
          "label": "Stepan Samko",
          "data": [
            -1,
            -8,
            -13,
            -17,
            -20,
            -21,
            -23,
            -25,
            -27,
            -28,
            -34,
            -37,
            -41,
            -50,
            -51,
            -52,
            -48,
            -46,
            -49,
            -50,
            -49,
            -50,
            -51,
            -50,
            -56,
            -64,
            -68,
            -69,
            -73,
            -78,
            -86,
            -90,
            -94,
            -97,
            -94,
            -89,
            -92,
            -93,
            -97,
            -112,
            -116,
            -114,
            -109,
            -105,
            -111,
            -105,
            -114,
            -116,
            -106,
            -96
          ],
          "fill": false
        }
      ]
    }
  }
}
